django_camel_field/__init__.py
django_camel_field/fields.py
django_camel_field-0.0.1.dist-info/METADATA
django_camel_field-0.0.1.dist-info/RECORD
django_camel_field-0.0.1.dist-info/WHEEL
django_camel_field-0.0.1.dist-info/top_level.txt
