Metadata-Version: 2.1
Name: django-camel-field
Version: 0.0.1
Summary: ForeignKey/OneToOneField with Camel Case Attribute Name
Home-page: https://github.com/zhangi/django_camel_field
Author: Ivan Zhang
Author-email: sail4dream@gmail.com
License: UNKNOWN
Platform: UNKNOWN
Classifier: Programming Language :: Python :: 3
Classifier: License :: OSI Approved :: MIT License
Classifier: Operating System :: OS Independent
